perplexity_search_cli/__init__.py
perplexity_search_cli/cli.py
perplexity_search_cli-1.0.6.dist-info/licenses/LICENSE
perplexity_search_cli-1.0.6.dist-info/METADATA
perplexity_search_cli-1.0.6.dist-info/WHEEL
perplexity_search_cli-1.0.6.dist-info/entry_points.txt
perplexity_search_cli-1.0.6.dist-info/top_level.txt
perplexity_search_cli-1.0.6.dist-info/RECORD
