Metadata-Version: 2.4
Name: perplexity-search-cli
Version: 1.0.6
Summary: Command line interface for Perplexity AI API
Author: Yuting Zhang
License: Apache-2.0
Classifier: License :: OSI Approved :: Apache Software License
Requires-Python: >=3.6
License-File: LICENSE
Requires-Dist: requests>=2.31.0
Dynamic: license-file
